flamehaven_filesearch/__init__.py
flamehaven_filesearch/admin_routes.py
flamehaven_filesearch/api.py
flamehaven_filesearch/auth.py
flamehaven_filesearch/batch_routes.py
flamehaven_filesearch/cache.py
flamehaven_filesearch/cache_redis.py
flamehaven_filesearch/config.py
flamehaven_filesearch/core.py
flamehaven_filesearch/dashboard.py
flamehaven_filesearch/encryption.py
flamehaven_filesearch/exceptions.py
flamehaven_filesearch/logging_config.py
flamehaven_filesearch/metrics.py
flamehaven_filesearch/middlewares.py
flamehaven_filesearch/multimodal.py
flamehaven_filesearch/oauth.py
flamehaven_filesearch/quantizer.py
flamehaven_filesearch/security.py
flamehaven_filesearch/storage.py
flamehaven_filesearch/validators.py
flamehaven_filesearch/vector_store.py
flamehaven_filesearch/engine/__init__.py
flamehaven_filesearch/engine/chronos_grid.py
flamehaven_filesearch/engine/embedding_generator.py
flamehaven_filesearch/engine/embedding_generator_legacy.py
flamehaven_filesearch/engine/gravitas_pack.py
flamehaven_filesearch/engine/intent_refiner.py
flamehaven_filesearch-1.4.0.dist-info/licenses/LICENSE
flamehaven_filesearch-1.4.0.dist-info/METADATA
flamehaven_filesearch-1.4.0.dist-info/WHEEL
flamehaven_filesearch-1.4.0.dist-info/entry_points.txt
flamehaven_filesearch-1.4.0.dist-info/top_level.txt
flamehaven_filesearch-1.4.0.dist-info/RECORD
