Metadata-Version: 2.4
Name: flamehaven-filesearch
Version: 1.4.0
Summary: FLAMEHAVEN FileSearch - Open source semantic document search with API authentication powered by Google Gemini
Author-email: FLAMEHAVEN <info@flamehaven.space>
Project-URL: Homepage, https://github.com/flamehaven01/Flamehaven-Filesearch
Project-URL: Documentation, https://github.com/flamehaven01/Flamehaven-Filesearch#readme
Project-URL: Repository, https://github.com/flamehaven01/Flamehaven-Filesearch
Project-URL: Bug Tracker, https://github.com/flamehaven01/Flamehaven-Filesearch/issues
Keywords: flamehaven,file-search,document-search,RAG,gemini,google-ai,file-retrieval,semantic-search
Classifier: Development Status :: 4 - Beta
Classifier: Intended Audience :: Developers
Classifier: Programming Language :: Python :: 3
Classifier: Programming Language :: Python :: 3.8
Classifier: Programming Language :: Python :: 3.9
Classifier: Programming Language :: Python :: 3.10
Classifier: Programming Language :: Python :: 3.11
Classifier: Programming Language :: Python :: 3.12
Classifier: Topic :: Software Development :: Libraries :: Python Modules
Classifier: Topic :: Scientific/Engineering :: Artificial Intelligence
Requires-Python: >=3.8
License-File: LICENSE
Requires-Dist: pydantic>=2.0.0
Requires-Dist: cryptography>=42.0.0
Provides-Extra: api
Requires-Dist: fastapi>=0.121.1; extra == "api"
Requires-Dist: uvicorn[standard]>=0.24.0; extra == "api"
Requires-Dist: python-multipart>=0.0.6; extra == "api"
Requires-Dist: slowapi>=0.1.9; extra == "api"
Requires-Dist: requests>=2.31.0; extra == "api"
Requires-Dist: psutil>=5.9.0; extra == "api"
Requires-Dist: python-json-logger>=2.0.0; extra == "api"
Requires-Dist: cachetools>=5.3.0; extra == "api"
Requires-Dist: prometheus-client>=0.19.0; extra == "api"
Requires-Dist: PyJWT>=2.8.0; extra == "api"
Provides-Extra: vector
Requires-Dist: hnswlib>=0.8.0; extra == "vector"
Provides-Extra: postgres
Requires-Dist: psycopg[binary]>=3.1.0; extra == "postgres"
Requires-Dist: pgvector>=0.2.5; extra == "postgres"
Provides-Extra: vision
Requires-Dist: pillow>=10.0.0; extra == "vision"
Requires-Dist: pytesseract>=0.3.10; extra == "vision"
Provides-Extra: dev
Requires-Dist: pytest>=7.0.0; extra == "dev"
Requires-Dist: pytest-cov>=4.0.0; extra == "dev"
Requires-Dist: pytest-asyncio>=0.21.0; extra == "dev"
Requires-Dist: black>=23.0.0; extra == "dev"
Requires-Dist: flake8>=6.0.0; extra == "dev"
Requires-Dist: mypy>=1.0.0; extra == "dev"
Requires-Dist: isort>=5.12.0; extra == "dev"
Requires-Dist: httpx>=0.24.1; extra == "dev"
Requires-Dist: numpy>=1.24.0; extra == "dev"
Provides-Extra: google
Requires-Dist: google-genai>=0.2.0; extra == "google"
Provides-Extra: security
Requires-Dist: bandit>=1.7.0; extra == "security"
Requires-Dist: safety>=3.0.0; extra == "security"
Provides-Extra: all
Requires-Dist: flamehaven-filesearch[api,dev,google,postgres,vector,vision]; extra == "all"
Dynamic: license-file
